test/__init__.py
test/test.py
universalid/__init__.py
universalid/encode.py
universalid/settings.py
universalid/universalid.py
universalid-1.0.0.dist-info/LICENSE.txt
universalid-1.0.0.dist-info/METADATA
universalid-1.0.0.dist-info/WHEEL
universalid-1.0.0.dist-info/top_level.txt
universalid-1.0.0.dist-info/RECORD
