Metadata-Version: 2.1
Name: universalid
Version: 1.0.0
Summary: UUID with built-in creation date
Home-page: https://github.com/majkilde/universalid.git
Author: Jakob Majkilde
Author-email: jakob@mjakilde.dk
License: UNKNOWN
Platform: UNKNOWN
Classifier: Programming Language :: Python :: 3
Classifier: License :: OSI Approved :: MIT License
Classifier: Operating System :: OS Independent
